privex/adminplus/__init__.py
privex/adminplus/admin.py
privex/adminplus/apps.py
privex/adminplus/settings.py
privex/adminplus/backports/__init__.py
privex/adminplus/backports/apps.py
privex/adminplus/backports/templates/admin/app_list.html
privex/adminplus/backports/templatetags/__init__.py
privex/adminplus/backports/templatetags/blocktranslate.py
privex/adminplus/templates/admin/custom_pages_box.html
privex/adminplus/templates/admin/index.html
privex/adminplus/templates/admin/nav_sidebar.html
privex_adminplus-1.0.0.dist-info/LICENSE
privex_adminplus-1.0.0.dist-info/METADATA
privex_adminplus-1.0.0.dist-info/WHEEL
privex_adminplus-1.0.0.dist-info/top_level.txt
privex_adminplus-1.0.0.dist-info/RECORD
