Metadata-Version: 2.1
Name: privex-adminplus
Version: 1.0.0
Summary: Similar to django-adminplus - a Django app allowing custom views with a list in the admin panel
Home-page: https://github.com/Privex/adminplus
Author: Chris (Someguy123) @ Privex
Author-email: chris@privex.io
License: MIT
Platform: UNKNOWN
Classifier: Programming Language :: Python :: 3
Classifier: Programming Language :: Python :: 3.6
Classifier: Programming Language :: Python :: 3.7
Classifier: Programming Language :: Python :: 3.8
Classifier: Framework :: Django
Classifier: Framework :: Django :: 2.0
Classifier: Framework :: Django :: 2.1
Classifier: Framework :: Django :: 2.2
Classifier: Framework :: Django :: 3.0
Classifier: License :: OSI Approved :: MIT License
Classifier: Operating System :: OS Independent
Requires-Dist: Django
Requires-Dist: privex-helpers (>=2.18.0)
